invenio_pidstore_extra/__init__.py
invenio_pidstore_extra/config.py
invenio_pidstore_extra/dnb-sandbox.py
invenio_pidstore_extra/ext.py
invenio_pidstore_extra/providers/__init__.py
invenio_pidstore_extra/providers/dnb.py
invenio_pidstore_extra/providers/urn/__init__.py
invenio_pidstore_extra/providers/urn/errors.py
invenio_pidstore_extra/providers/urn/request.py
invenio_pidstore_extra/providers/urn/rest.py
invenio_pidstore_extra/services/__init__.py
invenio_pidstore_extra/services/components/__init__.py
invenio_pidstore_extra/services/components/pids.py
invenio_pidstore_extra-0.2.0.dist-info/METADATA
invenio_pidstore_extra-0.2.0.dist-info/WHEEL
invenio_pidstore_extra-0.2.0.dist-info/entry_points.txt
invenio_pidstore_extra-0.2.0.dist-info/licenses/AUTHORS.rst
invenio_pidstore_extra-0.2.0.dist-info/licenses/LICENSE
invenio_pidstore_extra-0.2.0.dist-info/RECORD
